claude_lint/__init__.py
claude_lint/__version__.py
claude_lint/api_client.py
claude_lint/batch_processor.py
claude_lint/cache.py
claude_lint/cli.py
claude_lint/collector.py
claude_lint/config.py
claude_lint/constants.py
claude_lint/file_reader.py
claude_lint/file_utils.py
claude_lint/git_utils.py
claude_lint/guidelines.py
claude_lint/logging_config.py
claude_lint/metrics.py
claude_lint/orchestrator.py
claude_lint/processor.py
claude_lint/progress.py
claude_lint/rate_limiter.py
claude_lint/reporter.py
claude_lint/retry.py
claude_lint/types.py
claude_lint/validation.py
lint_claude-0.3.2.dist-info/licenses/LICENSE
lint_claude-0.3.2.dist-info/METADATA
lint_claude-0.3.2.dist-info/WHEEL
lint_claude-0.3.2.dist-info/entry_points.txt
lint_claude-0.3.2.dist-info/top_level.txt
lint_claude-0.3.2.dist-info/RECORD
