Metadata-Version: 2.4
Name: lint-claude
Version: 0.3.2
Summary: Enforce your CLAUDE.md guidelines using Claude AI - intelligent linting for agent instructions
Author-email: Vlad Temian <vladtemian@gmail.com>
Maintainer-email: Vlad Temian <vladtemian@gmail.com>
License: MIT
Project-URL: Homepage, https://github.com/vtemian/lint-claude
Project-URL: Documentation, https://github.com/vtemian/lint-claude/blob/main/README.md
Project-URL: Repository, https://github.com/vtemian/lint-claude
Project-URL: Issues, https://github.com/vtemian/lint-claude/issues
Project-URL: Changelog, https://github.com/vtemian/lint-claude/blob/main/CHANGELOG.md
Keywords: ai-agent,linter,code-quality,compliance,claude,anthropic,static-analysis,guidelines
Classifier: Development Status :: 4 - Beta
Classifier: Intended Audience :: Developers
Classifier: Topic :: Software Development :: Quality Assurance
Classifier: Topic :: Software Development :: Testing
Classifier: License :: OSI Approved :: MIT License
Classifier: Programming Language :: Python :: 3
Classifier: Programming Language :: Python :: 3.11
Classifier: Programming Language :: Python :: 3.12
Classifier: Typing :: Typed
Requires-Python: >=3.11
License-File: LICENSE
Requires-Dist: anthropic<0.50,>=0.18.0
Requires-Dist: click<9.0,>=8.1.0
Requires-Dist: rich<14.0,>=13.0.0
Requires-Dist: pydantic<3.0,>=2.0.0
Provides-Extra: dev
Requires-Dist: pytest<8.0,>=7.4.0; extra == "dev"
Requires-Dist: pytest-cov<5.0,>=4.1.0; extra == "dev"
Requires-Dist: ruff<0.3,>=0.1.0; extra == "dev"
Requires-Dist: mypy<2.0,>=1.8.0; extra == "dev"
Requires-Dist: pre-commit<4.0,>=3.5.0; extra == "dev"
Dynamic: license-file
